stitcher/__init__.py
stitcher/__main__.py
stitcher/api.py
stitcher/cg.py
stitcher/node.py
stitcher/stitcher.py
pycg_stitch-0.0.8.dist-info/LICENCE
pycg_stitch-0.0.8.dist-info/METADATA
pycg_stitch-0.0.8.dist-info/WHEEL
pycg_stitch-0.0.8.dist-info/entry_points.txt
pycg_stitch-0.0.8.dist-info/top_level.txt
pycg_stitch-0.0.8.dist-info/RECORD
